LICENSE
MANIFEST.in
README.rst
requirements.txt
setup.cfg
setup.py
visyerres_sgdf_woob/__init__.py
visyerres_sgdf_woob/capabilities.py
visyerres_sgdf_woob/errors.py
visyerres_sgdf_woob/mshtml.py
visyerres_sgdf_woob/utils.py
visyerres_sgdf_woob/version.py
visyerres_sgdf_woob.egg-info/PKG-INFO
visyerres_sgdf_woob.egg-info/SOURCES.txt
visyerres_sgdf_woob.egg-info/dependency_links.txt
visyerres_sgdf_woob.egg-info/not-zip-safe
visyerres_sgdf_woob.egg-info/requires.txt
visyerres_sgdf_woob.egg-info/top_level.txt
visyerres_sgdf_woob/modules/__init__.py
visyerres_sgdf_woob/modules/comptawebsgdf/__init__.py
visyerres_sgdf_woob/modules/comptawebsgdf/browser.py
visyerres_sgdf_woob/modules/comptawebsgdf/pages.py
visyerres_sgdf_woob/modules/intranetsgdf/__init__.py
visyerres_sgdf_woob/modules/intranetsgdf/api/__init__.py
visyerres_sgdf_woob/modules/intranetsgdf/api/browser.py
visyerres_sgdf_woob/modules/intranetsgdf/api/pages.py
visyerres_sgdf_woob/modules/intranetsgdf/directaccess/__init__.py
visyerres_sgdf_woob/modules/intranetsgdf/directaccess/browser.py
visyerres_sgdf_woob/modules/intranetsgdf/directaccess/elements.py
visyerres_sgdf_woob/modules/intranetsgdf/directaccess/filters.py
visyerres_sgdf_woob/modules/intranetsgdf/directaccess/pages.py
visyerres_sgdf_woob/modules/monprojetsgdf/__init__.py
visyerres_sgdf_woob/modules/monprojetsgdf/browser.py
visyerres_sgdf_woob/modules/monprojetsgdf/pages.py
visyerres_sgdf_woob/modules/ressourcessgdf/__init__.py
visyerres_sgdf_woob/modules/ressourcessgdf/browser.py
visyerres_sgdf_woob/modules/ressourcessgdf/pages.py