Metadata-Version: 1.2
Name: visyerres-sgdf-woob
Version: 20220216
Summary: woob modules for Scouts et Guides de France
Home-page: https://github.com/cakeisalie5/visyerres_sgdf_woob
Author: Thomas Touhey
Author-email: thomas@touhey.fr
License: MIT
Keywords: sgdf,intranet,woob
Platform: UNKNOWN
Requires-Python: >=3.9
